<?xml version="1.0" encoding="UTF-8"?>
<!DOCTYPE plist PUBLIC "-//Apple//DTD PLIST 1.0//EN" "http://www.apple.com/DTDs/PropertyList-1.0.dtd"/>

<plist version="1.0">
    <dict>
        <key>ROOT</key>
        <array>
            <dict>
                <key>id</key>
                <string>2682</string>
                <key>className</key>
                <string>PTModelLinker</string>
                <key>Name</key>
                <dict>
                    <key>visible</key>
                    <string>0</string>
                    <key>value</key>
                    <string></string>
                </dict>
            </dict>
            <dict>
                <key>id</key>
                <string>2683</string>
                <key>className</key>
                <string>PTModelLinker</string>
                <key>Name</key>
                <dict>
                    <key>visible</key>
                    <string>0</string>
                    <key>value</key>
                    <string></string>
                </dict>
            </dict>
            <dict>
                <key>id</key>
                <string>2684</string>
                <key>className</key>
                <string>PTModelLinker</string>
                <key>Name</key>
                <dict>
                    <key>visible</key>
                    <string>0</string>
                    <key>value</key>
                    <string></string>
                </dict>
            </dict>
            <dict>
                <key>id</key>
                <string>2685</string>
                <key>className</key>
                <string>PTModelLinker</string>
                <key>Name</key>
                <dict>
                    <key>visible</key>
                    <string>0</string>
                    <key>value</key>
                    <string></string>
                </dict>
            </dict>
            <dict>
                <key>id</key>
                <string>2686</string>
                <key>className</key>
                <string>PTModelLinker</string>
                <key>Name</key>
                <dict>
                    <key>visible</key>
                    <string>0</string>
                    <key>value</key>
                    <string></string>
                </dict>
            </dict>
            <dict>
                <key>id</key>
                <string>2687</string>
                <key>className</key>
                <string>PTModelLinker</string>
                <key>Name</key>
                <dict>
                    <key>visible</key>
                    <string>0</string>
                    <key>value</key>
                    <string></string>
                </dict>
            </dict>
            <dict>
                <key>id</key>
                <string>5631</string>
                <key>className</key>
                <string>PTModelLinker</string>
                <key>Name</key>
                <dict>
                    <key>visible</key>
                    <string>0</string>
                    <key>value</key>
                    <string></string>
                </dict>
            </dict>
            <dict>
                <key>id</key>
                <string>9506</string>
                <key>className</key>
                <string>PTModelLinker</string>
                <key>Name</key>
                <dict>
                    <key>visible</key>
                    <string>0</string>
                    <key>value</key>
                    <string></string>
                </dict>
            </dict>
            <dict>
                <key>id</key>
                <string>9507</string>
                <key>className</key>
                <string>PTModelLinker</string>
                <key>Name</key>
                <dict>
                    <key>visible</key>
                    <string>0</string>
                    <key>value</key>
                    <string></string>
                </dict>
            </dict>
            <dict>
                <key>id</key>
                <string>9563</string>
                <key>className</key>
                <string>PTModelLinker</string>
                <key>Name</key>
                <dict>
                    <key>visible</key>
                    <string>0</string>
                    <key>value</key>
                    <string></string>
                </dict>
            </dict>
            <dict>
                <key>id</key>
                <string>9564</string>
                <key>className</key>
                <string>PTModelLinker</string>
                <key>Name</key>
                <dict>
                    <key>visible</key>
                    <string>0</string>
                    <key>value</key>
                    <string></string>
                </dict>
            </dict>
            <dict>
                <key>id</key>
                <string>9565</string>
                <key>className</key>
                <string>PTModelLinker</string>
                <key>Name</key>
                <dict>
                    <key>visible</key>
                    <string>0</string>
                    <key>value</key>
                    <string></string>
                </dict>
            </dict>
            <dict>
                <key>id</key>
                <string>9566</string>
                <key>className</key>
                <string>PTModelLinker</string>
                <key>Name</key>
                <dict>
                    <key>visible</key>
                    <string>0</string>
                    <key>value</key>
                    <string></string>
                </dict>
            </dict>
            <dict>
                <key>id</key>
                <string>11509</string>
                <key>className</key>
                <string>PTModelLinker</string>
                <key>Name</key>
                <dict>
                    <key>visible</key>
                    <string>0</string>
                    <key>value</key>
                    <string></string>
                </dict>
            </dict>
            <dict>
                <key>id</key>
                <string>11510</string>
                <key>className</key>
                <string>PTModelLinker</string>
                <key>Name</key>
                <dict>
                    <key>visible</key>
                    <string>0</string>
                    <key>value</key>
                    <string></string>
                </dict>
            </dict>
            <dict>
                <key>id</key>
                <string>11511</string>
                <key>className</key>
                <string>PTModelLinker</string>
                <key>Name</key>
                <dict>
                    <key>visible</key>
                    <string>0</string>
                    <key>value</key>
                    <string></string>
                </dict>
            </dict>
            <dict>
                <key>id</key>
                <string>11512</string>
                <key>className</key>
                <string>PTModelLinker</string>
                <key>Name</key>
                <dict>
                    <key>visible</key>
                    <string>0</string>
                    <key>value</key>
                    <string></string>
                </dict>
            </dict>
            <dict>
                <key>id</key>
                <string>11513</string>
                <key>className</key>
                <string>PTModelLinker</string>
                <key>Name</key>
                <dict>
                    <key>visible</key>
                    <string>0</string>
                    <key>value</key>
                    <string></string>
                </dict>
            </dict>
        </array>
    </dict>
</plist>
